<xsd:dEvReg><gGroupGesEve xmlns="http://ekuatia.set.gov.py/sifen/xsd" xmlns:xsi="http://www.w3.org/2001/XMLSchema-instance" xsi:schemaLocation="http://ekuatia.set.gov.py/sifen/xsd siRecepEvento_v150.xsd"><rGesEve xmlns="http://ekuatia.set.gov.py/sifen/xsd"><rEve Id="4"><dFecFirma>2025-02-15T12:32:00</dFecFirma><dVerFor>150</dVerFor><gGroupTiEvt><rGeVeInu><dNumTim>12559587</dNumTim><dEst>001</dEst><dPunExp>001</dPunExp><dNumIn>0200588</dNumIn><dNumFin>0200588</dNumFin><iTiDE>01</iTiDE><mOtEve>Error al facturar</mOtEve></rGeVeInu></gGroupTiEvt></rEve></rGesEve></gGroupGesEve></xsd:dEvReg>